time_box/__init__.py
time_box/time_box.py
time_box-0.0.11.dist-info/METADATA
time_box-0.0.11.dist-info/WHEEL
time_box-0.0.11.dist-info/top_level.txt
time_box-0.0.11.dist-info/RECORD
