Metadata-Version: 2.1
Name: time-box
Version: 0.0.11
Summary: Time processing tool collection
Home-page: https://gitee.com/ZeroSeeker/timebox
Author: ZeroSeeker
Author-email: zeroseeker@foxmail.com
License: UNKNOWN
Platform: UNKNOWN
Classifier: Programming Language :: Python :: 3
Classifier: License :: OSI Approved :: MIT License
Classifier: Operating System :: OS Independent
Requires-Dist: pytz (==2021.3)
